Metadata-Version: 2.1
Name: greeting-by-time
Version: 0.1
Summary: Generating a welcome message for a specific time of day depending on the current hour.
Home-page: UNKNOWN
Author-email: beeeirym@gmail.com
License: UNKNOWN
Platform: UNKNOWN
